[
    {
        "lable": "Brick and Tile Makers -Where any machinery is used;excl. clay or blaes getting below 6 metres",
        "value": "Brick and Tile Makers -Where any machinery is used;excl. clay or blaes getting below 6 metres"
    },
    {
        "lable":"Builders - construction incl civil constructions",
        "value":"Builders - construction incl civil constructions"
    },
    {
        "lable":"Cable Laying, installation  erection work - away from shop / yard risk",
        "value":"Cable Laying, installation  erection work - away from shop / yard risk"
    },
    {
        "lable":"able Laying, installation  erection work - shop / yard risk",
        "value":"able Laying, installation  erection work - shop / yard risk"
    },
    {
        "lable":"Caretakers Durwans, Chowkidars and Gatekeepers",
        "value":"Caretakers Durwans, Chowkidars and Gatekeepers"
    },
    {
        "lable":"Carpenters",
        "value":"Carpenters"
    },
    {
        "lable":"Cement works (excl Quarry  Mining risk)",
        "value":"Cement works (excl Quarry  Mining risk)"
    },
    {
        "lable":"Clothing  Underclothing Mfgrs",
        "value":"Clothing  Underclothing Mfgrs"
    },
    {
        "lable":"Commercial Travellersv",
        "value":"Commercial Travellers"
    },
    {
        "lable":"Domestic Servants",
        "value":"Domestic Servants"
    },
    {
        "lable":"Electricity - Power supply",
        "value":"Electricity - Power supply"
    },
    {
        "lable":"Engineering workshop  Fabrication works (Above 9 meters)",
        "value":"Engineering workshop  Fabrication works (Above 9 meters)"
    },
    {
        "lable":"Hotels - indoor",
        "value":"Hotels - indoor"
    },
    {
        "lable":"Indoor Clerical works",
        "value":"Indoor Clerical works"
    },
    {
        "lable":"Loading and Unloading",
        "value":"Loading and Unloading"
    },
    {
        "lable":"Metal Workers",
        "value":"Metal Workers"
    },
    {
        "lable":"Painters  Decorators (not builder)",
        "value":"Painters  Decorators (not builder)"
    },
    {
        "lable":"Paper Mfgr",
        "value":"Paper Mfgr"
    },
    {
        "lable":"Pharma, Chemists  Druggists",
        "value":"Pharma, Chemists  Druggists"
    },
    {
        "lable":"Plastic Goods Mfgrs",
        "value":"Plastic Goods Mfgrs"
    },
    {
        "lable":"Road Paving, Tarring and Road Making",
        "value":"Road Paving, Tarring and Road Making"
    },
    {
        "lable":"Steel works",
        "value":"Steel works"
    },
    {
        "lable":"Yarn Production",
        "value":"Yarn Production"
    }
]